[
  {
    "ts": "2025-10-24T00:00:00Z",
    "val": 5.849
  },
  {
    "ts": "2025-10-24T00:10:00Z",
    "val": 5.943
  },
  {
    "ts": "2025-10-24T00:20:00Z",
    "val": 5.973
  },
  {
    "ts": "2025-10-24T00:30:00Z",
    "val": 6.142
  },
  {
    "ts": "2025-10-24T00:40:00Z",
    "val": 6.262
  },
  {
    "ts": "2025-10-24T00:50:00Z",
    "val": 6.396
  },
  {
    "ts": "2025-10-24T01:00:00Z",
    "val": 6.484
  },
  {
    "ts": "2025-10-24T01:10:00Z",
    "val": 6.553
  },
  {
    "ts": "2025-10-24T01:20:00Z",
    "val": 6.562
  },
  {
    "ts": "2025-10-24T01:30:00Z",
    "val": 6.722
  },
  {
    "ts": "2025-10-24T01:40:00Z",
    "val": 6.768
  },
  {
    "ts": "2025-10-24T01:50:00Z",
    "val": 6.992
  },
  {
    "ts": "2025-10-24T02:00:00Z",
    "val": 7.096
  },
  {
    "ts": "2025-10-24T02:10:00Z",
    "val": 7.065
  },
  {
    "ts": "2025-10-24T02:20:00Z",
    "val": 7.225
  },
  {
    "ts": "2025-10-24T02:30:00Z",
    "val": 7.353
  },
  {
    "ts": "2025-10-24T02:40:00Z",
    "val": 7.498
  },
  {
    "ts": "2025-10-24T02:50:00Z",
    "val": 7.436
  },
  {
    "ts": "2025-10-24T03:00:00Z",
    "val": 7.676
  },
  {
    "ts": "2025-10-24T03:10:00Z",
    "val": 7.727
  },
  {
    "ts": "2025-10-24T03:20:00Z",
    "val": 7.839
  },
  {
    "ts": "2025-10-24T03:30:00Z",
    "val": 7.92
  },
  {
    "ts": "2025-10-24T03:40:00Z",
    "val": 7.968
  },
  {
    "ts": "2025-10-24T03:50:00Z",
    "val": 8.195
  },
  {
    "ts": "2025-10-24T04:00:00Z",
    "val": 5.798
  },
  {
    "ts": "2025-10-24T04:10:00Z",
    "val": 5.838
  },
  {
    "ts": "2025-10-24T04:20:00Z",
    "val": 5.953
  },
  {
    "ts": "2025-10-24T04:30:00Z",
    "val": 6.155
  },
  {
    "ts": "2025-10-24T04:40:00Z",
    "val": 6.261
  },
  {
    "ts": "2025-10-24T04:50:00Z",
    "val": 6.362
  },
  {
    "ts": "2025-10-24T05:00:00Z",
    "val": 6.389
  },
  {
    "ts": "2025-10-24T05:10:00Z",
    "val": 6.539
  },
  {
    "ts": "2025-10-24T05:20:00Z",
    "val": 6.527
  },
  {
    "ts": "2025-10-24T05:30:00Z",
    "val": 6.602
  },
  {
    "ts": "2025-10-24T05:40:00Z",
    "val": 6.794
  },
  {
    "ts": "2025-10-24T05:50:00Z",
    "val": 6.962
  },
  {
    "ts": "2025-10-24T06:00:00Z",
    "val": 6.908
  },
  {
    "ts": "2025-10-24T06:10:00Z",
    "val": 7.166
  },
  {
    "ts": "2025-10-24T06:20:00Z",
    "val": 7.267
  },
  {
    "ts": "2025-10-24T06:30:00Z",
    "val": 7.319
  },
  {
    "ts": "2025-10-24T06:40:00Z",
    "val": 7.344
  },
  {
    "ts": "2025-10-24T06:50:00Z",
    "val": 7.405
  },
  {
    "ts": "2025-10-24T07:00:00Z",
    "val": 7.52
  },
  {
    "ts": "2025-10-24T07:10:00Z",
    "val": 7.765
  },
  {
    "ts": "2025-10-24T07:20:00Z",
    "val": 7.739
  },
  {
    "ts": "2025-10-24T07:30:00Z",
    "val": 7.984
  },
  {
    "ts": "2025-10-24T07:40:00Z",
    "val": 7.955
  },
  {
    "ts": "2025-10-24T07:50:00Z",
    "val": 8.089
  },
  {
    "ts": "2025-10-24T08:00:00Z",
    "val": 5.706
  },
  {
    "ts": "2025-10-24T08:10:00Z",
    "val": 5.874
  },
  {
    "ts": "2025-10-24T08:20:00Z",
    "val": 6.073
  },
  {
    "ts": "2025-10-24T08:30:00Z",
    "val": 6.146
  },
  {
    "ts": "2025-10-24T08:40:00Z",
    "val": 6.281
  },
  {
    "ts": "2025-10-24T08:50:00Z",
    "val": 6.319
  },
  {
    "ts": "2025-10-24T09:00:00Z",
    "val": 6.413
  },
  {
    "ts": "2025-10-24T09:10:00Z",
    "val": 6.485
  },
  {
    "ts": "2025-10-24T09:20:00Z",
    "val": 6.595
  },
  {
    "ts": "2025-10-24T09:30:00Z",
    "val": 6.648
  },
  {
    "ts": "2025-10-24T09:40:00Z",
    "val": 6.786
  },
  {
    "ts": "2025-10-24T09:50:00Z",
    "val": 6.889
  },
  {
    "ts": "2025-10-24T10:00:00Z",
    "val": 7.026
  },
  {
    "ts": "2025-10-24T10:10:00Z",
    "val": 7.122
  },
  {
    "ts": "2025-10-24T10:20:00Z",
    "val": 7.291
  },
  {
    "ts": "2025-10-24T10:30:00Z",
    "val": 7.378
  },
  {
    "ts": "2025-10-24T10:40:00Z",
    "val": 7.355
  },
  {
    "ts": "2025-10-24T10:50:00Z",
    "val": 7.57
  },
  {
    "ts": "2025-10-24T11:00:00Z",
    "val": 7.608
  },
  {
    "ts": "2025-10-24T11:10:00Z",
    "val": 7.756
  },
  {
    "ts": "2025-10-24T11:20:00Z",
    "val": 7.703
  },
  {
    "ts": "2025-10-24T11:30:00Z",
    "val": 7.899
  },
  {
    "ts": "2025-10-24T11:40:00Z",
    "val": 7.967
  },
  {
    "ts": "2025-10-24T11:50:00Z",
    "val": 8.194
  },
  {
    "ts": "2025-10-24T12:00:00Z",
    "val": 5.847
  },
  {
    "ts": "2025-10-24T12:10:00Z",
    "val": 5.866
  },
  {
    "ts": "2025-10-24T12:20:00Z",
    "val": 6.015
  },
  {
    "ts": "2025-10-24T12:30:00Z",
    "val": 6.094
  },
  {
    "ts": "2025-10-24T12:40:00Z",
    "val": 6.134
  },
  {
    "ts": "2025-10-24T12:50:00Z",
    "val": 6.344
  },
  {
    "ts": "2025-10-24T13:00:00Z",
    "val": 6.389
  },
  {
    "ts": "2025-10-24T13:10:00Z",
    "val": 6.447
  },
  {
    "ts": "2025-10-24T13:20:00Z",
    "val": 6.684
  },
  {
    "ts": "2025-10-24T13:30:00Z",
    "val": 6.669
  },
  {
    "ts": "2025-10-24T13:40:00Z",
    "val": 6.738
  },
  {
    "ts": "2025-10-24T13:50:00Z",
    "val": 6.88
  },
  {
    "ts": "2025-10-24T14:00:00Z",
    "val": 6.938
  },
  {
    "ts": "2025-10-24T14:10:00Z",
    "val": 7.107
  },
  {
    "ts": "2025-10-24T14:20:00Z",
    "val": 7.297
  },
  {
    "ts": "2025-10-24T14:30:00Z",
    "val": 7.296
  },
  {
    "ts": "2025-10-24T14:40:00Z",
    "val": 7.348
  },
  {
    "ts": "2025-10-24T14:50:00Z",
    "val": 7.576
  },
  {
    "ts": "2025-10-24T15:00:00Z",
    "val": 7.644
  },
  {
    "ts": "2025-10-24T15:10:00Z",
    "val": 7.679
  },
  {
    "ts": "2025-10-24T15:20:00Z",
    "val": 7.844
  },
  {
    "ts": "2025-10-24T15:30:00Z",
    "val": 7.983
  },
  {
    "ts": "2025-10-24T15:40:00Z",
    "val": 7.955
  },
  {
    "ts": "2025-10-24T15:50:00Z",
    "val": 8.091
  },
  {
    "ts": "2025-10-24T16:00:00Z",
    "val": 5.785
  },
  {
    "ts": "2025-10-24T16:10:00Z",
    "val": 5.863
  },
  {
    "ts": "2025-10-24T16:20:00Z",
    "val": 5.931
  },
  {
    "ts": "2025-10-24T16:30:00Z",
    "val": 6.056
  },
  {
    "ts": "2025-10-24T16:40:00Z",
    "val": 6.157
  },
  {
    "ts": "2025-10-24T16:50:00Z",
    "val": 6.274
  },
  {
    "ts": "2025-10-24T17:00:00Z",
    "val": 6.316
  },
  {
    "ts": "2025-10-24T17:10:00Z",
    "val": 6.406
  },
  {
    "ts": "2025-10-24T17:20:00Z",
    "val": 6.625
  },
  {
    "ts": "2025-10-24T17:30:00Z",
    "val": 6.675
  },
  {
    "ts": "2025-10-24T17:40:00Z",
    "val": 6.753
  },
  {
    "ts": "2025-10-24T17:50:00Z",
    "val": 6.831
  },
  {
    "ts": "2025-10-24T18:00:00Z",
    "val": 7.004
  },
  {
    "ts": "2025-10-24T18:10:00Z",
    "val": 7.069
  },
  {
    "ts": "2025-10-24T18:20:00Z",
    "val": 7.253
  },
  {
    "ts": "2025-10-24T18:30:00Z",
    "val": 7.333
  },
  {
    "ts": "2025-10-24T18:40:00Z",
    "val": 7.411
  },
  {
    "ts": "2025-10-24T18:50:00Z",
    "val": 7.471
  },
  {
    "ts": "2025-10-24T19:00:00Z",
    "val": 7.595
  },
  {
    "ts": "2025-10-24T19:10:00Z",
    "val": 7.609
  },
  {
    "ts": "2025-10-24T19:20:00Z",
    "val": 7.851
  },
  {
    "ts": "2025-10-24T19:30:00Z",
    "val": 7.824
  },
  {
    "ts": "2025-10-24T19:40:00Z",
    "val": 8.07
  },
  {
    "ts": "2025-10-24T19:50:00Z",
    "val": 8.036
  },
  {
    "ts": "2025-10-24T20:00:00Z",
    "val": 5.863
  },
  {
    "ts": "2025-10-24T20:10:00Z",
    "val": 5.911
  },
  {
    "ts": "2025-10-24T20:20:00Z",
    "val": 6.035
  },
  {
    "ts": "2025-10-24T20:30:00Z",
    "val": 6.149
  },
  {
    "ts": "2025-10-24T20:40:00Z",
    "val": 6.28
  },
  {
    "ts": "2025-10-24T20:50:00Z",
    "val": 6.248
  },
  {
    "ts": "2025-10-24T21:00:00Z",
    "val": 6.401
  },
  {
    "ts": "2025-10-24T21:10:00Z",
    "val": 6.527
  },
  {
    "ts": "2025-10-24T21:20:00Z",
    "val": 6.596
  },
  {
    "ts": "2025-10-24T21:30:00Z",
    "val": 6.616
  },
  {
    "ts": "2025-10-24T21:40:00Z",
    "val": 6.719
  },
  {
    "ts": "2025-10-24T21:50:00Z",
    "val": 6.996
  },
  {
    "ts": "2025-10-24T22:00:00Z",
    "val": 6.912
  },
  {
    "ts": "2025-10-24T22:10:00Z",
    "val": 7.098
  },
  {
    "ts": "2025-10-24T22:20:00Z",
    "val": 7.215
  },
  {
    "ts": "2025-10-24T22:30:00Z",
    "val": 7.296
  },
  {
    "ts": "2025-10-24T22:40:00Z",
    "val": 7.399
  },
  {
    "ts": "2025-10-24T22:50:00Z",
    "val": 7.576
  },
  {
    "ts": "2025-10-24T23:00:00Z",
    "val": 7.665
  },
  {
    "ts": "2025-10-24T23:10:00Z",
    "val": 7.718
  },
  {
    "ts": "2025-10-24T23:20:00Z",
    "val": 7.759
  },
  {
    "ts": "2025-10-24T23:30:00Z",
    "val": 7.99
  },
  {
    "ts": "2025-10-24T23:40:00Z",
    "val": 8.031
  },
  {
    "ts": "2025-10-24T23:50:00Z",
    "val": 8.191
  }
]